apifipecons/__init__.py
api_fipe_consumo_RPSJR-0.0.1.dist-info/METADATA
api_fipe_consumo_RPSJR-0.0.1.dist-info/WHEEL
api_fipe_consumo_RPSJR-0.0.1.dist-info/top_level.txt
api_fipe_consumo_RPSJR-0.0.1.dist-info/RECORD
