Metadata-Version: 2.1
Name: api-fipe-consumo-RPSJR
Version: 0.0.1
Summary: Metodos par aconsumo de API da FIPE
Home-page: https://github.com/pypa/sampleproject
Author: RAIMUNDO PEREIRA DA SILVA JUNIOR
Author-email: raimundopsjr@gmail.com
License: UNKNOWN
Platform: UNKNOWN
Classifier: Programming Language :: Python :: 3
Classifier: License :: OSI Approved :: MIT License
Classifier: Operating System :: OS Independent
Requires-Python: >=3.6
